ejcli/__init__.py
ejcli/__main__.py
ejcli/bashhelper.py
ejcli/cmd.py
ejcli/error.py
ejcli/hook_stdio.py
ejcli/_http/__init__.py
ejcli/_http/base.py
ejcli/_http/cache.py
ejcli/_http/codeforces.py
ejcli/_http/cupsonline.py
ejcli/_http/file.py
ejcli/_http/html2md.py
ejcli/_http/informatics.py
ejcli/_http/jjs.py
ejcli/_http/openerwr.py
ejcli/_http/types.py
ejcli/_http/yacontest.py
ejcli/_http/ejudge/__init__.py
ejcli/_http/ejudge/ej371.py
ejcli/_http/ejudge/ej373.py
ejcli/_http/ejudge/ejfuse.py
ejcli/_http/gcj/__init__.py
ejcli/_http/gcj/oauth.py
ejcli/_http/gcj/oauth_old.py
ejcli/_http/gcj/oauth_phjs.py
ejcli/_http/pcms/__init__.py
ejcli/_http/pcms/libpcms.py
ejcli/commands/__init__.py
ejcli/commands/aformat.py
ejcli/commands/astatus.py
ejcli/commands/clars.py
ejcli/commands/control.py
ejcli/commands/getfile.py
ejcli/commands/getsource.py
ejcli/commands/googlelogin.py
ejcli/commands/info.py
ejcli/commands/locale.py
ejcli/commands/passwd.py
ejcli/commands/samples.py
ejcli/commands/scoreboard.py
ejcli/commands/taskalias.py
ejcli/commands/watch.py
ejcli/commands/asubmit/__init__.py
ejcli/commands/asubmit/format_asm.py
ejcli/commands/asubmit/format_c.py
ejcli/commands/asubmit/format_cexpr.py
ejcli/commands/asubmit/format_cmd.py
ejcli/commands/asubmit/format_cpp.py
ejcli/commands/asubmit/format_none.py
ejcli/commands/asubmit/format_py.py
ejcli/commands/asubmit/format_str.py
ejcli/http/__init__.py
ejcli/http/base.py
ejcli-1.9.7.dist-info/LICENSE
ejcli-1.9.7.dist-info/METADATA
ejcli-1.9.7.dist-info/WHEEL
ejcli-1.9.7.dist-info/entry_points.txt
ejcli-1.9.7.dist-info/top_level.txt
ejcli-1.9.7.dist-info/RECORD
