Metadata-Version: 2.1
Name: ejcli
Version: 1.9.7
Summary: A testing system console client
License-File: LICENSE
